{
  "last_updated": "2025-11-02",
  "season": "2025-26",
  "players": {
    "Dad": {
      "teams": [
        "Magic",
        "Pistons",
        "Pacers",
        "Suns",
        "Jazz"
      ],
      "wins": 12,
      "losses": 18,
      "earnings": -1.5
    },
    "Tyler": {
      "teams": [
        "Heat",
        "Thunder",
        "Bucks",
        "Raptors",
        "Nets"
      ],
      "wins": 15,
      "losses": 13,
      "earnings": 0.5
    },
    "Ethan": {
      "teams": [
        "76ers",
        "Mavericks",
        "Grizzlies",
        "Hawks",
        "Celtics"
      ],
      "wins": 15,
      "losses": 15,
      "earnings": 0.0
    },
    "Landon": {
      "teams": [
        "Trail Blazers",
        "Clippers",
        "Wizards",
        "Knicks",
        "Lakers"
      ],
      "wins": 14,
      "losses": 14,
      "earnings": 0.0
    },
    "Mom": {
      "teams": [
        "Rockets",
        "Nuggets",
        "Spurs",
        "Kings",
        "Bulls"
      ],
      "wins": 18,
      "losses": 8,
      "earnings": 2.5
    },
    "Micah": {
      "teams": [
        "Timberwolves",
        "Warriors",
        "Cavaliers",
        "Hornets",
        "Pelicans"
      ],
      "wins": 12,
      "losses": 18,
      "earnings": -1.5
    }
  },
  "team_records": {
    "Nets": {
      "wins": 0,
      "losses": 5
    },
    "Pacers": {
      "wins": 1,
      "losses": 5
    },
    "Wizards": {
      "wins": 1,
      "losses": 5
    },
    "Raptors": {
      "wins": 2,
      "losses": 4
    },
    "Hornets": {
      "wins": 2,
      "losses": 4
    },
    "Magic": {
      "wins": 3,
      "losses": 4
    },
    "Celtics": {
      "wins": 3,
      "losses": 4
    },
    "Knicks": {
      "wins": 2,
      "losses": 3
    },
    "Hawks": {
      "wins": 3,
      "losses": 3
    },
    "Cavaliers": {
      "wins": 3,
      "losses": 3
    },
    "Heat": {
      "wins": 3,
      "losses": 2
    },
    "Bucks": {
      "wins": 4,
      "losses": 2
    },
    "Pistons": {
      "wins": 4,
      "losses": 2
    },
    "76ers": {
      "wins": 4,
      "losses": 1
    },
    "Bulls": {
      "wins": 5,
      "losses": 0
    },
    "Pelicans": {
      "wins": 0,
      "losses": 5
    },
    "Suns": {
      "wins": 2,
      "losses": 4
    },
    "Kings": {
      "wins": 2,
      "losses": 4
    },
    "Mavericks": {
      "wins": 2,
      "losses": 4
    },
    "Jazz": {
      "wins": 2,
      "losses": 3
    },
    "Grizzlies": {
      "wins": 3,
      "losses": 3
    },
    "Timberwolves": {
      "wins": 3,
      "losses": 3
    },
    "Clippers": {
      "wins": 3,
      "losses": 2
    },
    "Nuggets": {
      "wins": 3,
      "losses": 2
    },
    "Rockets": {
      "wins": 3,
      "losses": 2
    },
    "Warriors": {
      "wins": 4,
      "losses": 3
    },
    "Trail Blazers": {
      "wins": 4,
      "losses": 2
    },
    "Lakers": {
      "wins": 4,
      "losses": 2
    },
    "Spurs": {
      "wins": 5,
      "losses": 0
    },
    "Thunder": {
      "wins": 6,
      "losses": 0
    }
  }
}