{
  "last_updated": "2025-11-15",
  "season": "2025-26",
  "players": {
    "Dad": {
      "teams": [
        "Magic",
        "Pistons",
        "Pacers",
        "Suns",
        "Jazz"
      ],
      "wins": 31,
      "losses": 32,
      "earnings": -0.25
    },
    "Tyler": {
      "teams": [
        "Heat",
        "Thunder",
        "Bucks",
        "Raptors",
        "Nets"
      ],
      "wins": 35,
      "losses": 28,
      "earnings": 1.75
    },
    "Ethan": {
      "teams": [
        "76ers",
        "Mavericks",
        "Grizzlies",
        "Hawks",
        "Celtics"
      ],
      "wins": 28,
      "losses": 36,
      "earnings": -2.0
    },
    "Landon": {
      "teams": [
        "Trail Blazers",
        "Clippers",
        "Wizards",
        "Knicks",
        "Lakers"
      ],
      "wins": 28,
      "losses": 33,
      "earnings": -1.25
    },
    "Mom": {
      "teams": [
        "Rockets",
        "Nuggets",
        "Spurs",
        "Kings",
        "Bulls"
      ],
      "wins": 34,
      "losses": 24,
      "earnings": 2.5
    },
    "Micah": {
      "teams": [
        "Timberwolves",
        "Warriors",
        "Cavaliers",
        "Hornets",
        "Pelicans"
      ],
      "wins": 30,
      "losses": 33,
      "earnings": -0.75
    }
  },
  "team_records": {
    "Nets": {
      "wins": 1,
      "losses": 11
    },
    "Pacers": {
      "wins": 1,
      "losses": 11
    },
    "Wizards": {
      "wins": 1,
      "losses": 11
    },
    "Hornets": {
      "wins": 4,
      "losses": 8
    },
    "Celtics": {
      "wins": 6,
      "losses": 7
    },
    "Bulls": {
      "wins": 6,
      "losses": 5
    },
    "Magic": {
      "wins": 7,
      "losses": 6
    },
    "Heat": {
      "wins": 7,
      "losses": 6
    },
    "76ers": {
      "wins": 7,
      "losses": 5
    },
    "Raptors": {
      "wins": 7,
      "losses": 5
    },
    "Hawks": {
      "wins": 8,
      "losses": 5
    },
    "Cavaliers": {
      "wins": 8,
      "losses": 5
    },
    "Bucks": {
      "wins": 8,
      "losses": 5
    },
    "Knicks": {
      "wins": 8,
      "losses": 4
    },
    "Pistons": {
      "wins": 11,
      "losses": 2
    },
    "Pelicans": {
      "wins": 2,
      "losses": 10
    },
    "Kings": {
      "wins": 3,
      "losses": 10
    },
    "Mavericks": {
      "wins": 3,
      "losses": 10
    },
    "Grizzlies": {
      "wins": 4,
      "losses": 9
    },
    "Jazz": {
      "wins": 4,
      "losses": 8
    },
    "Clippers": {
      "wins": 4,
      "losses": 8
    },
    "Trail Blazers": {
      "wins": 6,
      "losses": 6
    },
    "Warriors": {
      "wins": 8,
      "losses": 6
    },
    "Suns": {
      "wins": 8,
      "losses": 5
    },
    "Timberwolves": {
      "wins": 8,
      "losses": 4
    },
    "Spurs": {
      "wins": 8,
      "losses": 4
    },
    "Rockets": {
      "wins": 8,
      "losses": 3
    },
    "Lakers": {
      "wins": 9,
      "losses": 4
    },
    "Nuggets": {
      "wins": 9,
      "losses": 2
    },
    "Thunder": {
      "wins": 12,
      "losses": 1
    }
  }
}